README.md
setup.py
weather_connect/__init__.py
weather_connect/weather_connect.py
weather_connect.egg-info/PKG-INFO
weather_connect.egg-info/SOURCES.txt
weather_connect.egg-info/dependency_links.txt
weather_connect.egg-info/requires.txt
weather_connect.egg-info/top_level.txt