Metadata-Version: 2.1
Name: weather_connect
Version: 0.1.0
Summary: weather connect library
Author: Faclon-Labs
Author-email: reachus@faclon.com
Classifier: Programming Language :: Python :: 3
Classifier: License :: OSI Approved :: MIT License
Classifier: Operating System :: OS Independent
Requires-Dist: pymongo
Requires-Dist: pandas
Requires-Dist: requests
Requires-Dist: datetime
